liboauth2
