Metadata-Version: 1.1
Name: liboauth2
Version: 0.0.2
Summary: Light Python wrapper for the OAuth 2.0 protocol
Home-page: http://github.com/zakzou/liboauth2
Author: zakzou
Author-email: zakzou@live.com
License: MIT
Keywords: OAuth2 Client,OAuth2
Platform: any
Classifier: Environment :: Web Environment
Classifier: Intended Audience :: Developers
Classifier: License :: OSI Approved :: MIT License
Classifier: Operating System :: OS Independent
Classifier: Programming Language :: Python
